{
  "users": [
    {
      "id": "1",
      "username": "user1",
      "password": "password1"
    },
    {
      "id": "2",
      "username": "user2",
      "password": "password2"
    },
    {
      "id": "47a4",
      "username": "user1",
      "password": "password1"
    },
    {
      "id": "5c84",
      "username": "user1",
      "password": "password1"
    },
    {
      "id": "448d",
      "username": "test1",
      "password": "password1"
    },
    {
      "id": "084e",
      "username": "testuser1",
      "password": "testpassword1"
    },
    {
      "id": "ed24",
      "username": "test1",
      "password": "password1"
    },
    {
      "id": "92d4",
      "username": "yoonki99",
      "password": "whdbsrl123"
    }
  ]
}